{"homebrew_version":"2.1.14-44-g2bf8015","used_options":[],"unused_options":[],"built_as_bottle":true,"poured_from_bottle":true,"installed_as_dependency":false,"installed_on_request":true,"changed_files":["share/rt-audio/tests/apinames","share/rt-audio/tests/audioprobe","share/rt-audio/tests/duplex","share/rt-audio/tests/playraw","share/rt-audio/tests/playsaw","share/rt-audio/tests/record","share/rt-audio/tests/testall","share/rt-audio/tests/teststops","INSTALL_RECEIPT.json","lib/pkgconfig/rtaudio.pc","share/doc/rt-audio/Makefile","share/rt-audio/tests/Makefile"],"time":1611647953,"source_modified_time":1555698999,"HEAD":null,"stdlib":"libcxx","compiler":"clang","aliases":[],"runtime_dependencies":[],"source":{"path":"/usr/local/Homebrew/Library/Taps/homebrew/homebrew-core/Formula/rt-audio.rb","tap":"homebrew/core","spec":"stable","versions":{"stable":"5.1.0","devel":"","head":"HEAD","version_scheme":0}},"arch":"x86_64","built_on":null}